winsys/__init__.py
winsys/_advapi32.py
winsys/_compat.py
winsys/_kernel32.py
winsys/_lsa.py
winsys/accounts.py
winsys/active_directory.py
winsys/constants.py
winsys/core.py
winsys/dialogs.py
winsys/encryption.py
winsys/environment.py
winsys/event_logs.py
winsys/exc.py
winsys/fs.py
winsys/handles.py
winsys/ipc.py
winsys/logging_handlers.py
winsys/misc.py
winsys/processes.py
winsys/registry.py
winsys/scheduled_tasks.py
winsys/security.py
winsys/shell.py
winsys/utils.py
winsys/_security/__init__.py
winsys/_security/_aces.py
winsys/_security/_acls.py
winsys/_security/_privileges.py
winsys/_security/_tokens.py
winsys/_security/core.py
winsys/extras/isapi_monitor.py
winsys/extras/monitor_directory.py
winsys-1.2.dist-info/LICENSE.txt
winsys-1.2.dist-info/METADATA
winsys-1.2.dist-info/WHEEL
winsys-1.2.dist-info/top_level.txt
winsys-1.2.dist-info/RECORD
