Metadata-Version: 2.1
Name: winsys
Version: 1.2
Summary: WinSys: the Python Windows Administrator's Toolkit
Home-page: https://winsys.readthedocs.io/
Author: Tim Golden
Author-email: mail@timgolden.me.uk
License: MIT
Platform: win32
Classifier: Development Status :: 4 - Beta
Classifier: Environment :: Console
Classifier: Intended Audience :: System Administrators
Classifier: License :: OSI Approved :: MIT License
Classifier: Operating System :: Microsoft :: Windows :: Windows NT/2000
Classifier: Programming Language :: Python :: 3
Classifier: Topic :: Utilities
Provides-Extra: tests
Provides-Extra: dev
Provides-Extra: package
Provides-Extra: docs
Provides-Extra: all
